cncore/__init__.py
cncore/idioms.py
cncore/zebra.py
cnflask/__init__.py
cnflask/app.py
merchantkit/__init__.py
merchantkit-0.0.1.dist-info/licenses/LICENSE
merchantkit-0.0.1.dist-info/METADATA
merchantkit-0.0.1.dist-info/WHEEL
merchantkit-0.0.1.dist-info/top_level.txt
merchantkit-0.0.1.dist-info/RECORD
