Metadata-Version: 2.4
Name: merchantkit
Version: 0.0.1
Summary: E-commerce operations toolkit for Python (in development)
Home-page: https://github.com/merchantkit/merchantkit
Author: MerchantKit Contributors
Author-email: merchantkit@example.com
Project-URL: Documentation, https://github.com/merchantkit/merchantkit
Project-URL: Source, https://github.com/merchantkit/merchantkit
Project-URL: Tracker, https://github.com/merchantkit/merchantkit/issues
Keywords: ecommerce commerce toolkit merchant orders fulfillment inventory catalog shipping
Classifier: Development Status :: 1 - Planning
Classifier: Intended Audience :: Developers
Classifier: Topic :: Office/Business
Classifier: Topic :: Software Development :: Libraries :: Python Modules
Classifier: License :: OSI Approved :: MIT License
Classifier: Programming Language :: Python :: 3
Classifier: Programming Language :: Python :: 3.8
Classifier: Programming Language :: Python :: 3.9
Classifier: Programming Language :: Python :: 3.10
Classifier: Programming Language :: Python :: 3.11
Classifier: Programming Language :: Python :: 3.12
Requires-Python: >=3.8
License-File: LICENSE
Dynamic: author
Dynamic: author-email
Dynamic: classifier
Dynamic: description-content-type
Dynamic: home-page
Dynamic: keywords
Dynamic: license-file
Dynamic: project-url
Dynamic: requires-python
Dynamic: summary
